acme_nginx/AWSRoute53.py
acme_nginx/Acme.py
acme_nginx/AcmeV2.py
acme_nginx/Cloudflare.py
acme_nginx/DigitalOcean.py
acme_nginx/__init__.py
acme_nginx/client.py
acme_nginx-0.5.0.dist-info/WHEEL
acme_nginx-0.5.0.dist-info/entry_points.txt
acme_nginx-0.5.0.dist-info/METADATA
acme_nginx-0.5.0.dist-info/RECORD
