Metadata-Version: 2.4
Name: acme-nginx
Version: 0.5.0
Summary: Python library/program to create LetsEncrypt SSL certificates
Author: Konstantin Shcherban
Author-email: Konstantin Shcherban <insider@sudoers.dev>
License-Expression: GPL-3.0
Requires-Dist: boto3~=1.34
Requires-Dist: cryptography~=45.0
Requires-Dist: pytest~=8.3 ; extra == 'test'
Requires-Python: >=3.9.2, <3.14
Project-URL: homepage, https://github.com/kshcherban/acme-nginx
Project-URL: repository, https://github.com/kshcherban/acme-nginx
Provides-Extra: dev
Provides-Extra: test
